{
    "src":[
        "img/1.jpg",
        "img/2.jpg",
        "img/3.jpg",
        "img/4.jpg",
        "img/5.jpg",
        "img/6.jpg",
        "img/7.jpg",
        "img/8.jpg",
        "img/9.jpg",
        "img/10.jpg",
        "img/11.jpg",
        "img/12.jpg",
        "img/13.jpg",
        "img/14.jpg",
        "img/15.jpg",
        "img/16.jpg",
        "img/17.jpg",
        "img/18.jpg",
        "img/19.jpg",
        "img/20.jpg",
        "img/21.jpg",
        "img/22.jpg",
        "img/23.jpg",
        "img/24.jpg",
        "img/25.jpg",
        "img/26.jpg",
        "img/27.jpg",
        "img/28.jpg",
        "img/29.jpg",
        "img/30.jpg",
        "img/31.jpg",
        "img/32.jpg",
        "img/33.jpg",
        "img/34.jpg",
        "img/35.jpg",
        "img/36.jpg",
        "img/37.jpg",
        "img/38.jpg",
        "img/39.jpg",
        "img/40.jpg",
        "img/41.jpg",
        "img/42.jpg",
        "img/43.jpg",
        "img/44.jpg",
        "img/45.jpg",
        "img/46.jpg",
        "img/47.jpg",
        "img/48.jpg",
        "img/49.jpg",
        "img/50.jpg",
        "img/51.jpg",
        "img/52.jpg",
        "img/53.jpg",
        "img/54.jpg"








    ],
    "p1":[
        "告别低效,人人必备的聪明工作法",
        "送训练营,王培峰EXCEL实战课",
        "王牌课程瑞普的ppt超神课",
        "快速精通Project项目管理2.0版",
        "26堂PPT实操课打通制作思维",
        "数码单反摄影高手速成",
        "手机摄影高手速成-精品王牌首选",
        "交互式PPT",
        "8零基础/进阶/案例/全程通关",
        "人人用得上的思维导图课",
        "产品经理方法论+实战",
        "深度有趣-人工智能实战集合",
        "AI前奏必备-数据结构C语言版",
        "数据科学人工智能-必备数学基础",
        "【企业级】大数据项目实践",
        "Python数据分析与机器学习实战",
        "撩课-Vue核心技术+商城项目实战",
        "新媒体营销短视频入门到精通",
        "社群营销赚钱系统-引流成交裂变",
        "软文高手速成-营销文案写作秘籍",
        "抖音APP产品实战(产品经理课)",
        "视频营销赚钱推品牌入门精通",
        "如何从0到1成为百家号运营高手",
        "新媒体营销 微博自运营攻略",
        "零基础变身营销达人—311人学过",
        "习惯管理:活出全方位的高效率",
        "高效学习:职场身价倍增的秘籍",
        "七天战胜拖延症-提升执行力绝招",
        "如何有效提升你的职场影响力",
        "职场商务礼仪速成-职业形象打造",
        "高效时间管理-效率提升终极秘诀",
        "工资外收入如何从0到月入10万",
        "月光族赚钱必修:0-30万财富积累",
        "如何高回报投资比特币,区块链",
        "周小树基金定投高级篇:智慧定投",
        "理财小白入门必修课",
        "小白理财,月入3000撬动百万收益",
        "学了就能用的理财进阶手册",
        "脱离死工资,步入财富快车道",
        "全新外教演绎自然拼读法",
        "记忆大师教你快速提升记忆力",
        "英语思维:快速建立语法体系",
        "英语口语革命",
        "从零基础小白轻松玩转手绘插画",
        "手绘POP插画完整详解",
        "赵可赛:这一次彻底搞懂葡萄酒",
        "11节鸡尾酒社交课,秒变社交达人",
        "10万人在学的零基础成人钢琴课",
        "零基础瑜伽拉伸,给肩颈放个假",
        "7分钟燃脂操--28天完整版",
        "健美冠军教你练出细直大长腿",
        "瘦身普拉提 减肥健身必备",
        "5分钟办公间隙健身改善不良体态",
        "5分钟办公间隙健身改善不良体态"

    ],
    "span":[
        "共23课时 | 3892人学过",
        "共56课时 | 3892人学过",
        "共28课时 | 3892人学过",
        "共21课时 | 3892人学过",
        "共23课时 | 3892人学过",
        "共54课时 | 3892人学过",
        "共76课时 | 3892人学过",
        "共236课时 | 3892人学过",
        "共154课时 | 3892人学过",
        "共12课时 | 3892人学过",
        "共96课时 | 3892人学过",
        "共12课时 | 3892人学过",
        "共78课时 | 3892人学过",
        "共20课时 | 3892人学过",
        "共78课时 | 3892人学过",
        "共36课时 | 3892人学过",
        "共95课时 | 3892人学过",
        "共78课时 | 3892人学过",
        "共62课时 | 3892人学过",
        "共45课时 | 3892人学过",
        "共26课时 | 3892人学过",
        "共82课时 | 3892人学过",
        "共15课时 | 3892人学过",
        "共23课时 | 3892人学过",
        "共75课时 | 3892人学过",
        "共15课时 | 3892人学过",
        "共66课时 | 3892人学过",
        "共12课时 | 3892人学过",
        "共96课时 | 3892人学过",
        "共50课时 | 3892人学过",
        "共45课时 | 3892人学过",
        "共12课时 | 3892人学过",
        "共96课时 | 3892人学过",
        "共12课时 | 3892人学过",
        "共96课时 | 3892人学过",
        "共46课时 | 3892人学过",
        "共36课时 | 3892人学过",
        "共96课时 | 3892人学过",
        "共45课时 | 3892人学过",
        "共12课时 | 3892人学过",
        "共59课时 | 3892人学过",
        "共79课时 | 3892人学过",
        "共8课时 | 3892人学过",
        "共23课时 | 3892人学过",
        "共95课时 | 3892人学过",
        "共123课时 | 3892人学过",
        "共93课时 | 3892人学过",
        "共93课时 | 3892人学过",
        "共73课时 | 3892人学过",
        "共26课时 | 3892人学过",
        "共15课时 | 3892人学过",
        "共89课时 | 3892人学过",
        "共15课时 | 3892人学过",
        "共78课时 | 3892人学过"






    ],
    "p2":[
        "￥99.00",
        "￥198.00",
        "￥199.00",
        "￥299.00",
        "￥699.00",
        "￥599.00",
        "￥99.00",
        "￥94.00",
        "￥498.00",
        "￥499.00",
        "￥59.00",
        "￥299.00",
        "￥199.00",
        "￥97.00",
        "￥199.00",
        "￥299.00",
        "￥399.00",
        "￥199.00",
        "￥299.00",
        "￥399.00",
        "￥499.00",
        "￥599.00",
        "￥899.00",
        "￥799.00",
        "￥299.00",
        "￥98.00",
        "￥199.00",
        "￥299.00",
        "￥399.00",
        "￥499.00",
        "￥599.00",
        "￥299.00",
        "￥399.00",
        "￥599.00",
        "￥299.00",
        "￥399.00",
        "￥599.00",
        "￥199.00",
        "￥399.00",
        "￥499.00",
        "￥98.00",
        "￥499.00",
        "￥199.00",
        "￥299.00",
        "￥699.00",
        "￥799.00",
        "￥299.00",
        "￥199.00",
        "￥399.00",
        "￥499.00",
        "￥599.00",
        "￥399.00",
        "￥499.00",
        "￥199.00"



    ],
    "div":[
        "赚￥29.90",
        "赚￥19.90",
        "赚￥9.90",
        "赚￥19.90",
        "赚￥39.90",
        "赚￥29.90",
        "赚￥19.90",
        "赚￥9.90",
        "赚￥29.90",
        "赚￥9.90",
        "赚￥29.90",
        "赚￥9.90",
        "赚￥29.90",
        "赚￥9.90",
        "赚￥19.90",
        "赚￥29.90",
        "赚￥28.90",
        "赚￥29.90",
        "赚￥59.90",
        "赚￥279.90",
        "赚￥29.80",
        "赚￥29.60",
        "赚￥29.90",
        "赚￥39.90",
        "赚￥29.90",
        "赚￥29.70",
        "赚￥29.90",
        "赚￥29.60",
        "赚￥29.90",
        "赚￥49.90",
        "赚￥29.40",
        "赚￥29.90",
        "赚￥59.90",
        "赚￥29.90",
        "赚￥9.90",
        "赚￥29.90",
        "赚￥29.90",
        "赚￥9.90",
        "赚￥29.70",
        "赚￥9.90",
        "赚￥29.90",
        "赚￥9.90",
        "赚￥29.90",
        "赚￥9.90",
        "赚￥29.80",
        "赚￥29.90",
        "赚￥29.90",
        "赚￥29.90",
        "赚￥99.90",
        "赚￥29.90",
        "赚￥19.90",
        "赚￥29.90",
        "赚￥29.50",
        "赚￥79.90"



    ]
}